nplot/__init__.py
nplot/bar_plot.py
nplot/consts.py
nplot/figure_size.py
nplot/grid_style.py
nplot/line_plot.py
nplot/plot_bar_style.py
nplot/plot_line_style.py
nplot/plot_scatter_style.py
nplot/scatter_plot.py
nplot/utils.py
nplot-2.2.0.dist-info/LICENSE
nplot-2.2.0.dist-info/METADATA
nplot-2.2.0.dist-info/NOTICE
nplot-2.2.0.dist-info/WHEEL
nplot-2.2.0.dist-info/top_level.txt
nplot-2.2.0.dist-info/RECORD
